instantpy/__init__.py
instantpy/instantpy.py
instantpy-0.0.3.dist-info/COPYING
instantpy-0.0.3.dist-info/METADATA
instantpy-0.0.3.dist-info/WHEEL
instantpy-0.0.3.dist-info/top_level.txt
instantpy-0.0.3.dist-info/RECORD
