Metadata-Version: 2.1
Name: instantpy
Version: 0.0.3
Summary: A Python wrapper for Aruba Instant REST API
Home-page: https://github.com/mww012/instantpy.git
Author: Michael Wood
Author-email: mww012@gmail.com
License: UNKNOWN
Platform: UNKNOWN
Classifier: Programming Language :: Python :: 3
Classifier: License :: OSI Approved :: MIT License
Classifier: Operating System :: OS Independent
Requires-Python: >=3.6
